flax_orbax/__init__.py
flax_orbax/checkpointer.py
flax_orbax/serialization.py
flax_orbax/tempsave.py
flax_orbax-0.1.4.dist-info/METADATA
flax_orbax-0.1.4.dist-info/WHEEL
flax_orbax-0.1.4.dist-info/RECORD
