Metadata-Version: 2.4
Name: flax_orbax
Version: 0.1.4
Summary: A package for saving JAX-compatible dataclasses with Orbax
Author-email: Dibya Ghosh <dibya@berkeley.edu>
Requires-Python: >=3.10
Requires-Dist: pyyaml
Provides-Extra: dev
Requires-Dist: ipykernel; extra == 'dev'
Provides-Extra: jax
Requires-Dist: flax; extra == 'jax'
Requires-Dist: orbax-checkpoint; extra == 'jax'
